README.md
setup.py
xpf/__init__.py
xpf/assist.py
xpf/connection.py
xpf/direct.py
xpf/failsafe.py
xpf/variables.py
xpf.egg-info/PKG-INFO
xpf.egg-info/SOURCES.txt
xpf.egg-info/dependency_links.txt
xpf.egg-info/top_level.txt