Metadata-Version: 2.1
Name: xpf
Version: 1.0.1
Summary: A python interface to interacting with p4 as a soft dependency
Home-page: https://github.com/mikemalinowski/xpf
Author: Mike Malinowski
Author-email: mike@twisted.space
License: UNKNOWN
Platform: UNKNOWN
Classifier: Programming Language :: Python
Classifier: License :: OSI Approved :: MIT License
Classifier: Operating System :: OS Independent
